obs3dian/.DS_Store
obs3dian/__init__.py
obs3dian/config.py
obs3dian/core.py
obs3dian/main.py
obs3dian/markdown.py
obs3dian/s3.py
obs3dian-0.3.3.dist-info/METADATA
obs3dian-0.3.3.dist-info/WHEEL
obs3dian-0.3.3.dist-info/entry_points.txt
obs3dian-0.3.3.dist-info/RECORD
